{
 "generated_utc": "2026-06-12T01:22:05+00:00",
 "source": "Yahoo Finance (quarterly trailing YoY metrics)",
 "criteria": {
  "growth_sweet": "EPS growth (trailing quarterly YoY) between 10 % and 40 % \u2014 fast but not frothy (Lynch sweet spot)",
  "peg_ok": "PEG ratio \u2264 1.5 \u2014 the primary gate; you're not paying up for growth",
  "rev_confirms": "Revenue growth \u2265 5 % \u2014 earnings growth backed by real sales",
  "roe_strong": "Return on equity \u2265 12 % \u2014 management generating returns above cost of capital",
  "debt_ok": "Debt/equity \u2264 1.0 (skipped for Financials where leverage is structural)"
 },
 "coverage": {
  "universe": 515,
  "no_data": 7,
  "candidates": 30
 },
 "candidates": [
  {
   "ticker": "EME",
   "name": "Emcor",
   "sector": "Industrials",
   "mcap_b": 36.1,
   "price": 811.53,
   "pe": 27.3,
   "eps_growth_pct": 30.0,
   "peg": 0.44,
   "rev_growth_pct": 19.7,
   "roe_pct": 39.2,
   "de": 0.13,
   "checks": {
    "growth_sweet": true,
    "peg_ok": true,
    "rev_confirms": true,
    "roe_strong": true,
    "debt_ok": true
   },
   "score": 5,
   "anon": "CAND-01"
  },
  {
   "ticker": "ADBE",
   "name": "Adobe Inc.",
   "sector": "Information Technology",
   "mcap_b": 88.4,
   "price": 218.8,
   "pe": 12.5,
   "eps_growth_pct": 11.1,
   "peg": 0.62,
   "rev_growth_pct": 12.0,
   "roe_pct": 58.8,
   "de": 0.58,
   "checks": {
    "growth_sweet": true,
    "peg_ok": true,
    "rev_confirms": true,
    "roe_strong": true,
    "debt_ok": true
   },
   "score": 5,
   "anon": "CAND-02"
  },
  {
   "ticker": "INTU",
   "name": "Intuit",
   "sector": "Information Technology",
   "mcap_b": 75.7,
   "price": 276.91,
   "pe": 16.9,
   "eps_growth_pct": 10.7,
   "peg": 0.74,
   "rev_growth_pct": 10.4,
   "roe_pct": 22.5,
   "de": 0.33,
   "checks": {
    "growth_sweet": true,
    "peg_ok": true,
    "rev_confirms": true,
    "roe_strong": true,
    "debt_ok": true
   },
   "score": 5,
   "anon": "CAND-03"
  },
  {
   "ticker": "VEEV",
   "name": "Veeva Systems",
   "sector": "Health Care",
   "mcap_b": 26.2,
   "price": 161.55,
   "pe": 28.7,
   "eps_growth_pct": 14.6,
   "peg": 0.74,
   "rev_growth_pct": 16.3,
   "roe_pct": 13.9,
   "de": 0.01,
   "checks": {
    "growth_sweet": true,
    "peg_ok": true,
    "rev_confirms": true,
    "roe_strong": true,
    "debt_ok": true
   },
   "score": 5,
   "anon": "CAND-04"
  },
  {
   "ticker": "UHS",
   "name": "Universal Health Services",
   "sector": "Health Care",
   "mcap_b": 8.8,
   "price": 146.05,
   "pe": 6.1,
   "eps_growth_pct": 17.7,
   "peg": 1.01,
   "rev_growth_pct": 9.6,
   "roe_pct": 21.4,
   "de": 0.67,
   "checks": {
    "growth_sweet": true,
    "peg_ok": true,
    "rev_confirms": true,
    "roe_strong": true,
    "debt_ok": true
   },
   "score": 5,
   "anon": "CAND-05"
  },
  {
   "ticker": "EOG",
   "name": "EOG Resources",
   "sector": "Energy",
   "mcap_b": 72.7,
   "price": 136.53,
   "pe": 13.4,
   "eps_growth_pct": 39.6,
   "peg": 1.12,
   "rev_growth_pct": 15.6,
   "roe_pct": 18.2,
   "de": 0.27,
   "checks": {
    "growth_sweet": true,
    "peg_ok": true,
    "rev_confirms": true,
    "roe_strong": true,
    "debt_ok": true
   },
   "score": 5,
   "anon": "CAND-06"
  },
  {
   "ticker": "RMD",
   "name": "ResMed",
   "sector": "Health Care",
   "mcap_b": 27.9,
   "price": 192.39,
   "pe": 18.6,
   "eps_growth_pct": 10.5,
   "peg": 1.14,
   "rev_growth_pct": 10.8,
   "roe_pct": 25.2,
   "de": 0.13,
   "checks": {
    "growth_sweet": true,
    "peg_ok": true,
    "rev_confirms": true,
    "roe_strong": true,
    "debt_ok": true
   },
   "score": 5,
   "anon": "CAND-07"
  },
  {
   "ticker": "TXT",
   "name": "Textron",
   "sector": "Industrials",
   "mcap_b": 16.3,
   "price": 93.75,
   "pe": 17.9,
   "eps_growth_pct": 10.6,
   "peg": 1.17,
   "rev_growth_pct": 11.8,
   "roe_pct": 12.3,
   "de": 0.53,
   "checks": {
    "growth_sweet": true,
    "peg_ok": true,
    "rev_confirms": true,
    "roe_strong": true,
    "debt_ok": true
   },
   "score": 5,
   "anon": "CAND-08"
  },
  {
   "ticker": "MSFT",
   "name": "Microsoft",
   "sector": "Information Technology",
   "mcap_b": 2899.6,
   "price": 390.34,
   "pe": 23.2,
   "eps_growth_pct": 23.4,
   "peg": 1.27,
   "rev_growth_pct": 18.3,
   "roe_pct": 34.0,
   "de": 0.3,
   "checks": {
    "growth_sweet": true,
    "peg_ok": true,
    "rev_confirms": true,
    "roe_strong": true,
    "debt_ok": true
   },
   "score": 5,
   "anon": "CAND-09"
  },
  {
   "ticker": "KEYS",
   "name": "Keysight Technologies",
   "sector": "Information Technology",
   "mcap_b": 58.1,
   "price": 340.03,
   "pe": 54.7,
   "eps_growth_pct": 35.6,
   "peg": 1.39,
   "rev_growth_pct": 31.5,
   "roe_pct": 18.2,
   "de": 0.44,
   "checks": {
    "growth_sweet": true,
    "peg_ok": true,
    "rev_confirms": true,
    "roe_strong": true,
    "debt_ok": true
   },
   "score": 5,
   "anon": "CAND-10"
  },
  {
   "ticker": "TXN",
   "name": "Texas Instruments",
   "sector": "Information Technology",
   "mcap_b": 270.4,
   "price": 297.1,
   "pe": 50.8,
   "eps_growth_pct": 31.3,
   "peg": 1.42,
   "rev_growth_pct": 18.6,
   "roe_pct": 32.3,
   "de": 0.84,
   "checks": {
    "growth_sweet": true,
    "peg_ok": true,
    "rev_confirms": true,
    "roe_strong": true,
    "debt_ok": true
   },
   "score": 5,
   "anon": "CAND-11"
  },
  {
   "ticker": "MU",
   "name": "Micron Technology",
   "sector": "Information Technology",
   "mcap_b": 1123.1,
   "price": 995.87,
   "pe": 46.9,
   "eps_growth_pct": 756.0,
   "peg": 0.32,
   "rev_growth_pct": 196.3,
   "roe_pct": 39.8,
   "de": 0.15,
   "checks": {
    "growth_sweet": false,
    "peg_ok": true,
    "rev_confirms": true,
    "roe_strong": true,
    "debt_ok": true
   },
   "score": 4,
   "anon": "CAND-12"
  },
  {
   "ticker": "INCY",
   "name": "Incyte",
   "sector": "Health Care",
   "mcap_b": 21.5,
   "price": 107.83,
   "pe": 15.2,
   "eps_growth_pct": 83.8,
   "peg": 0.36,
   "rev_growth_pct": 20.9,
   "roe_pct": 30.8,
   "de": 0.01,
   "checks": {
    "growth_sweet": false,
    "peg_ok": true,
    "rev_confirms": true,
    "roe_strong": true,
    "debt_ok": true
   },
   "score": 4,
   "anon": "CAND-13"
  },
  {
   "ticker": "WDC",
   "name": "Western Digital",
   "sector": "Information Technology",
   "mcap_b": 182.4,
   "price": 529.29,
   "pe": 31.6,
   "eps_growth_pct": 482.9,
   "peg": 0.44,
   "rev_growth_pct": 45.5,
   "roe_pct": 85.9,
   "de": 0.18,
   "checks": {
    "growth_sweet": false,
    "peg_ok": true,
    "rev_confirms": true,
    "roe_strong": true,
    "debt_ok": true
   },
   "score": 4,
   "anon": "CAND-14"
  },
  {
   "ticker": "BSX",
   "name": "Boston Scientific",
   "sector": "Health Care",
   "mcap_b": 70.1,
   "price": 47.17,
   "pe": 19.7,
   "eps_growth_pct": 100.0,
   "peg": 0.59,
   "rev_growth_pct": 11.6,
   "roe_pct": 14.7,
   "de": 0.42,
   "checks": {
    "growth_sweet": false,
    "peg_ok": true,
    "rev_confirms": true,
    "roe_strong": true,
    "debt_ok": true
   },
   "score": 4,
   "anon": "CAND-15"
  },
  {
   "ticker": "APA",
   "name": "APA Corporation",
   "sector": "Energy",
   "mcap_b": 13.0,
   "price": 36.78,
   "pe": 8.6,
   "eps_growth_pct": 32.2,
   "peg": 0.64,
   "rev_growth_pct": -11.9,
   "roe_pct": 26.2,
   "de": 0.61,
   "checks": {
    "growth_sweet": true,
    "peg_ok": true,
    "rev_confirms": false,
    "roe_strong": true,
    "debt_ok": true
   },
   "score": 4,
   "anon": "CAND-16"
  },
  {
   "ticker": "NVDA",
   "name": "Nvidia",
   "sector": "Information Technology",
   "mcap_b": 4962.2,
   "price": 204.87,
   "pe": 31.4,
   "eps_growth_pct": 214.5,
   "peg": 0.64,
   "rev_growth_pct": 85.2,
   "roe_pct": 114.3,
   "de": 0.07,
   "checks": {
    "growth_sweet": false,
    "peg_ok": true,
    "rev_confirms": true,
    "roe_strong": true,
    "debt_ok": true
   },
   "score": 4,
   "anon": "CAND-17"
  },
  {
   "ticker": "ZBH",
   "name": "Zimmer Biomet",
   "sector": "Health Care",
   "mcap_b": 16.9,
   "price": 87.14,
   "pe": 22.6,
   "eps_growth_pct": 34.1,
   "peg": 0.64,
   "rev_growth_pct": 9.3,
   "roe_pct": 6.1,
   "de": 0.6,
   "checks": {
    "growth_sweet": true,
    "peg_ok": true,
    "rev_confirms": true,
    "roe_strong": false,
    "debt_ok": true
   },
   "score": 4,
   "anon": "CAND-18"
  },
  {
   "ticker": "FSLR",
   "name": "First Solar",
   "sector": "Information Technology",
   "mcap_b": 29.1,
   "price": 271.17,
   "pe": 17.5,
   "eps_growth_pct": 65.1,
   "peg": 0.65,
   "rev_growth_pct": 23.6,
   "roe_pct": 18.4,
   "de": 0.06,
   "checks": {
    "growth_sweet": false,
    "peg_ok": true,
    "rev_confirms": true,
    "roe_strong": true,
    "debt_ok": true
   },
   "score": 4,
   "anon": "CAND-19"
  },
  {
   "ticker": "AVGO",
   "name": "Broadcom",
   "sector": "Information Technology",
   "mcap_b": 1834.4,
   "price": 385.57,
   "pe": 63.9,
   "eps_growth_pct": 85.4,
   "peg": 0.7,
   "rev_growth_pct": 47.9,
   "roe_pct": 37.3,
   "de": 0.74,
   "checks": {
    "growth_sweet": false,
    "peg_ok": true,
    "rev_confirms": true,
    "roe_strong": true,
    "debt_ok": true
   },
   "score": 4,
   "anon": "CAND-20"
  },
  {
   "ticker": "IQV",
   "name": "IQVIA",
   "sector": "Health Care",
   "mcap_b": 30.2,
   "price": 181.06,
   "pe": 22.5,
   "eps_growth_pct": 15.0,
   "peg": 0.73,
   "rev_growth_pct": 8.4,
   "roe_pct": 22.5,
   "de": 2.55,
   "checks": {
    "growth_sweet": true,
    "peg_ok": true,
    "rev_confirms": true,
    "roe_strong": true,
    "debt_ok": false
   },
   "score": 4,
   "anon": "CAND-21"
  },
  {
   "ticker": "HWM",
   "name": "Howmet Aerospace",
   "sector": "Industrials",
   "mcap_b": 105.9,
   "price": 264.6,
   "pe": 61.2,
   "eps_growth_pct": 71.4,
   "peg": 0.8,
   "rev_growth_pct": 19.1,
   "roe_pct": 33.8,
   "de": 0.88,
   "checks": {
    "growth_sweet": false,
    "peg_ok": true,
    "rev_confirms": true,
    "roe_strong": true,
    "debt_ok": true
   },
   "score": 4,
   "anon": "CAND-22"
  },
  {
   "ticker": "META",
   "name": "Meta Platforms",
   "sector": "Communication Services",
   "mcap_b": 1442.9,
   "price": 568.43,
   "pe": 20.7,
   "eps_growth_pct": 62.4,
   "peg": 0.83,
   "rev_growth_pct": 33.1,
   "roe_pct": 32.9,
   "de": 0.36,
   "checks": {
    "growth_sweet": false,
    "peg_ok": true,
    "rev_confirms": true,
    "roe_strong": true,
    "debt_ok": true
   },
   "score": 4,
   "anon": "CAND-23"
  },
  {
   "ticker": "RJF",
   "name": "Raymond James Financial",
   "sector": "Financials",
   "mcap_b": 29.3,
   "price": 150.42,
   "pe": 14.2,
   "eps_growth_pct": 15.3,
   "peg": 0.84,
   "rev_growth_pct": 13.1,
   "roe_pct": 17.3,
   "de": 0.48,
   "checks": {
    "growth_sweet": true,
    "peg_ok": true,
    "rev_confirms": true,
    "roe_strong": true,
    "debt_ok": null
   },
   "score": 4,
   "anon": "CAND-24"
  },
  {
   "ticker": "ADSK",
   "name": "Autodesk",
   "sector": "Information Technology",
   "mcap_b": 43.4,
   "price": 205.57,
   "pe": 30.0,
   "eps_growth_pct": 231.4,
   "peg": 0.85,
   "rev_growth_pct": 18.4,
   "roe_pct": 50.4,
   "de": 0.85,
   "checks": {
    "growth_sweet": false,
    "peg_ok": true,
    "rev_confirms": true,
    "roe_strong": true,
    "debt_ok": true
   },
   "score": 4,
   "anon": "CAND-25"
  },
  {
   "ticker": "CTSH",
   "name": "Cognizant",
   "sector": "Information Technology",
   "mcap_b": 24.2,
   "price": 51.18,
   "pe": 11.1,
   "eps_growth_pct": 3.6,
   "peg": 0.85,
   "rev_growth_pct": 5.8,
   "roe_pct": 14.9,
   "de": 0.07,
   "checks": {
    "growth_sweet": false,
    "peg_ok": true,
    "rev_confirms": true,
    "roe_strong": true,
    "debt_ok": true
   },
   "score": 4,
   "anon": "CAND-26"
  },
  {
   "ticker": "FIX",
   "name": "Comfort Systems USA",
   "sector": "Industrials",
   "mcap_b": 64.9,
   "price": 1843.42,
   "pe": 53.3,
   "eps_growth_pct": 38.8,
   "peg": 0.87,
   "rev_growth_pct": 1.0,
   "roe_pct": 53.3,
   "de": 0.45,
   "checks": {
    "growth_sweet": true,
    "peg_ok": true,
    "rev_confirms": false,
    "roe_strong": true,
    "debt_ok": true
   },
   "score": 4,
   "anon": "CAND-27"
  },
  {
   "ticker": "CI",
   "name": "Cigna",
   "sector": "Health Care",
   "mcap_b": 78.0,
   "price": 294.84,
   "pe": 11.8,
   "eps_growth_pct": 29.1,
   "peg": 0.89,
   "rev_growth_pct": 4.6,
   "roe_pct": 16.3,
   "de": 0.73,
   "checks": {
    "growth_sweet": true,
    "peg_ok": true,
    "rev_confirms": false,
    "roe_strong": true,
    "debt_ok": true
   },
   "score": 4,
   "anon": "CAND-28"
  },
  {
   "ticker": "ALGN",
   "name": "Align Technology",
   "sector": "Health Care",
   "mcap_b": 12.6,
   "price": 176.51,
   "pe": 29.7,
   "eps_growth_pct": 23.9,
   "peg": 0.9,
   "rev_growth_pct": 6.2,
   "roe_pct": 10.8,
   "de": 0.03,
   "checks": {
    "growth_sweet": true,
    "peg_ok": true,
    "rev_confirms": true,
    "roe_strong": false,
    "debt_ok": true
   },
   "score": 4,
   "anon": "CAND-29"
  },
  {
   "ticker": "TTD",
   "name": "Trade Desk (The)",
   "sector": "Communication Services",
   "mcap_b": 8.9,
   "price": 18.9,
   "pe": 21.5,
   "eps_growth_pct": -20.0,
   "peg": 0.92,
   "rev_growth_pct": 11.8,
   "roe_pct": 16.7,
   "de": 0.17,
   "checks": {
    "growth_sweet": false,
    "peg_ok": true,
    "rev_confirms": true,
    "roe_strong": true,
    "debt_ok": true
   },
   "score": 4,
   "anon": "CAND-30"
  }
 ]
}